elcaminoreal/__init__.py
elcaminoreal/_errors.py
elcaminoreal/_gather.py
elcaminoreal/_version.py
elcaminoreal/test/__init__.py
elcaminoreal/test/__main__.py
elcaminoreal/test/some_plugins.py
elcaminoreal/test/test_gathering.py
elcaminoreal/test/voynich_main.py
elcaminoreal/test/voynich_skeleton.py
elcaminoreal-18.8.0.dist-info/METADATA
elcaminoreal-18.8.0.dist-info/RECORD
elcaminoreal-18.8.0.dist-info/WHEEL
elcaminoreal-18.8.0.dist-info/entry_points.txt
elcaminoreal-18.8.0.dist-info/top_level.txt
