Metadata-Version: 2.1
Name: elcaminoreal
Version: 18.8.0
Summary: El Camino Real: Bringing your things together.
Home-page: UNKNOWN
Author: Moshe Zadka
Author-email: zadka.moshe@gmail.com
License: MIT
Platform: UNKNOWN
Requires-Dist: attrs
Requires-Dist: incremental
Requires-Dist: gather
Requires-Dist: six
Requires-Dist: pyrsistent
Requires-Dist: caparg
